[{"__type__":"cc.SpriteFrame","content":{"name":"bg_game","texture":"b3bffB6EJGxp52R5d/giu5","rect":[0,0,1280,2772],"offset":[0,0],"originalSize":[1280,2772],"capInsets":[0,0,0,0]}},[{"__type__":"cc.SceneAsset","_name":"Game","scene":{"__id__":1},"asyncLoadAssets":null},{"__type__":"cc.Scene","_name":"New Node","_children":[{"__id__":2}],"_anchorPoint":{"__type__":"cc.Vec2"},"_trs":{"__type__":"TypedArray","ctor":"Float32Array","array":[0,0,0,0,0,0,1,1,1,1]},"autoReleaseAssets":false},{"__type__":"cc.Node","_name":"Canvas","_parent":{"__id__":1},"_children":[{"__id__":3},{"__id__":4},{"__id__":5},{"__id__":6},{"__id__":11}],"_components":[{"__type__":"cc.Canvas","node":{"__id__":2},"_designResolution":{"__type__":"cc.Size","width":1280,"height":720}},{"__type__":"98a8biRS9pO+ZCoV/dcLmUm","node":{"__id__":2},"bg1Node":{"__id__":4},"bg2Node":{"__id__":5},"distanceCounter":{"__id__":10},"plane":{"__id__":17},"rockScene":{"__id__":13}}],"_contentSize":{"__type__":"cc.Size","width":1280,"height":720},"_trs":{"__type__":"TypedArray","ctor":"Float32Array","array":[640,360,0,0,0,0,1,1,1,1]},"_id":"83Eya5w4RGXqmvmskyg38z"},{"__type__":"cc.Node","_name":"Main Camera","_parent":{"__id__":2},"_components":[{"__type__":"cc.Camera","node":{"__id__":3},"_clearFlags":7,"_depth":-1}],"_trs":{"__type__":"TypedArray","ctor":"Float32Array","array":[0,0,467.6537170410156,0,0,0,1,1,1,1]}},{"__type__":"cc.Node","_name":"bg1","_parent":{"__id__":2},"_components":[{"__type__":"cc.Sprite","node":{"__id__":4},"_materials":[{"__uuid__":"ecpdLyjvZBwrvm+cedCcQy"}],"_spriteFrame":{"__uuid__":"79v4ALX7NHTZ6s2coEDbP2"}},{"__type__":"cc.Widget","node":{"__id__":4},"_alignFlags":40,"_originalWidth":1280}],"_contentSize":{"__type__":"cc.Size","width":1280,"height":2772},"_trs":{"__type__":"TypedArray","ctor":"Float32Array","array":[0,0,0,0,0,0,1,1,1,1]}},{"__type__":"cc.Node","_name":"bg2","_parent":{"__id__":2},"_components":[{"__type__":"cc.Sprite","node":{"__id__":5},"_materials":[{"__uuid__":"ecpdLyjvZBwrvm+cedCcQy"}],"_spriteFrame":{"__uuid__":"79v4ALX7NHTZ6s2coEDbP2"}},{"__type__":"cc.Widget","node":{"__id__":5},"_alignFlags":40,"_originalWidth":1280}],"_contentSize":{"__type__":"cc.Size","width":1280,"height":2772},"_trs":{"__type__":"TypedArray","ctor":"Float32Array","array":[0,2772,0,0,0,0,1,1,1,1]}},{"__type__":"cc.Node","_name":"distance","_parent":{"__id__":2},"_children":[{"__id__":7},{"__id__":8}],"_components":[{"__type__":"cc.Widget","node":{"__id__":6},"_alignFlags":9,"_left":60,"_top":40},{"__type__":"cc.Layout","node":{"__id__":6},"_layoutSize":{"__type__":"cc.Size","width":186.76,"height":50.4},"_resize":1,"_N$layoutType":1},{"__id__":10}],"_color":{"__type__":"cc.Color","r":141,"g":232,"b":255},"_contentSize":{"__type__":"cc.Size","width":186.76,"height":50.4},"_anchorPoint":{"__type__":"cc.Vec2","y":0.5},"_trs":{"__type__":"TypedArray","ctor":"Float32Array","array":[-580,294.79998779296875,0,0,0,0,1,1,1,1]}},{"__type__":"cc.Node","_name":"label","_parent":{"__id__":6},"_components":[{"__type__":"cc.Label","node":{"__id__":7},"_materials":[{"__uuid__":"ecpdLyjvZBwrvm+cedCcQy"}],"_string":"Distance:","_N$string":"Distance:","_fontSize":28,"_lineHeight":28}],"_color":{"__type__":"cc.Color","r":141,"g":232,"b":255},"_contentSize":{"__type__":"cc.Size","width":116.72,"height":35.28},"_anchorPoint":{"__type__":"cc.Vec2","y":0.5},"_trs":{"__type__":"TypedArray","ctor":"Float32Array","array":[0,0,0,0,0,0,1,1,1,1]}},{"__type__":"cc.Node","_name":"count","_parent":{"__id__":6},"_components":[{"__id__":9}],"_color":{"__type__":"cc.Color","r":141,"g":232,"b":255},"_contentSize":{"__type__":"cc.Size","width":70.04,"height":35.28},"_anchorPoint":{"__type__":"cc.Vec2","y":0.5},"_trs":{"__type__":"TypedArray","ctor":"Float32Array","array":[116.72000122070312,0,0,0,0,0,1,1,1,1]}},{"__type__":"cc.Label","node":{"__id__":8},"_materials":[{"__uuid__":"ecpdLyjvZBwrvm+cedCcQy"}],"_string":"100m","_N$string":"100m","_fontSize":28,"_lineHeight":28},{"__type__":"e8b045PUslNFpdwHhxCdWwo","node":{"__id__":6},"distanceLabel":{"__id__":9}},{"__type__":"cc.Node","_name":"game_scene","_parent":{"__id__":2},"_children":[{"__id__":12},{"__id__":14}],"_components":[{"__type__":"cc.Widget","node":{"__id__":11},"_alignFlags":45}],"_contentSize":{"__type__":"cc.Size","width":1280,"height":720},"_trs":{"__type__":"TypedArray","ctor":"Float32Array","array":[0,0,0,0,0,0,1,1,1,1]}},{"__type__":"cc.Node","_name":"rock_scene","_parent":{"__id__":11},"_components":[{"__type__":"cc.Widget","node":{"__id__":12},"_alignFlags":45},{"__id__":13}],"_contentSize":{"__type__":"cc.Size","width":1280,"height":720},"_trs":{"__type__":"TypedArray","ctor":"Float32Array","array":[0,0,0,0,0,0,1,1,1,1]}},{"__type__":"9b1f8ZgOXlFcqmMYQYfn228","node":{"__id__":12}},{"__type__":"cc.Node","_name":"plane_scene","_parent":{"__id__":11},"_children":[{"__id__":15}],"_components":[{"__type__":"cc.Widget","node":{"__id__":14},"_alignFlags":45,"_originalHeight":161}],"_contentSize":{"__type__":"cc.Size","width":1280,"height":720},"_trs":{"__type__":"TypedArray","ctor":"Float32Array","array":[0,0,0,0,0,0,1,1,1,1]}},{"__type__":"cc.Node","_name":"plane","_parent":{"__id__":14},"_children":[{"__id__":16}],"_components":[{"__id__":17},{"__type__":"cc.BoxCollider","node":{"__id__":15},"_size":{"__type__":"cc.Size","width":181,"height":161}},{"__id__":18}],"_contentSize":{"__type__":"cc.Size","width":181,"height":161},"_trs":{"__type__":"TypedArray","ctor":"Float32Array","array":[0,-720,0,0,0,0,1,1,1,1]},"_groupIndex":1,"groupIndex":1},{"__type__":"cc.Node","_name":"tail_flame","_parent":{"__id__":15},"_components":[{"__type__":"sp.Skeleton","node":{"__id__":16},"_materials":[{"__uuid__":"7a/QZLET9IDreTiBfRn2PD"}],"defaultAnimation":"feiji1","_preCacheMode":0,"_animationName":"feiji1","_N$skeletonData":{"__uuid__":"6bh5w9UJVAdbgskvs6TOIa"}}],"_contentSize":{"__type__":"cc.Size","width":136,"height":174.5},"_trs":{"__type__":"TypedArray","ctor":"Float32Array","array":[0,-70,0,0,0,0,1,1,1,1]},"_groupIndex":1,"groupIndex":1},{"__type__":"bd7ec2F+GBJv4L9x89SWP4N","node":{"__id__":15},"commonDragView":{"__id__":18}},{"__type__":"df079+jUMlNWZLEcjTonSe4","node":{"__id__":15}}]]